pygouv.py
pygouv-0.1.0.dist-info/METADATA
pygouv-0.1.0.dist-info/WHEEL
pygouv-0.1.0.dist-info/top_level.txt
pygouv-0.1.0.dist-info/RECORD
