Metadata-Version: 2.1
Name: pygouv
Version: 0.1.0
Summary: API wrapper for data.gouv.fr
Home-page: https://github.com/feddelegrand7/pygouv
Author: Mohamed El Fodil Ihaddaden
Author-email: ihaddaden.fodeil@gmail.com
License: UNKNOWN
Platform: UNKNOWN
Classifier: Programming Language :: Python :: 3
Classifier: Programming Language :: Python :: 3.6
Classifier: Programming Language :: Python :: 3.7
Classifier: License :: OSI Approved :: GNU Affero General Public License v3
Classifier: Natural Language :: English
Requires-Dist: pandas (~=1.1)
Requires-Dist: requests (~=2.25)
Provides-Extra: dev
Requires-Dist: pytest (>=3.7) ; extra == 'dev'
